automatic_contract_creation/__init__.py
automatic_contract_creation/scr/__init__.py
automatic_contract_creation/scr/connectors/__init__.py
automatic_contract_creation/scr/connectors/click_connect.py
automatic_contract_creation/scr/connectors/click_dtypes.sql
automatic_contract_creation/scr/connectors/connection_manager.py
automatic_contract_creation/scr/connectors/connectors.py
automatic_contract_creation/scr/connectors/trino_connector.py
automatic_contract_creation/scr/connectors/trino_dtypes.sql
automatic_contract_creation/scr/generators/__init__.py
automatic_contract_creation/scr/generators/contract_variable.py
automatic_contract_creation/scr/generators/soda_generator.py
automatic_contract_creation/scr/llama/__init__.py
automatic_contract_creation/scr/llama/checks.py
automatic_contract_creation/scr/llama/duplicate_percent.py
automatic_contract_creation/scr/llama/invalid_percent.py
automatic_contract_creation/scr/llama/invalid_percent_min_max.py
automatic_contract_creation/scr/llama/invalid_percent_valid_regex.py
automatic_contract_creation/scr/llama/invalid_percent_valid_values.py
automatic_contract_creation/scr/llama/llama_description.py
automatic_contract_creation/scr/llama/llama_generate_sodacontract.py
automatic_contract_creation/scr/llama/llama_generate_suite.py
automatic_contract_creation/scr/llama/llama_model.py
automatic_contract_creation/scr/llama/missing_percent.py
automatic_contract_creation/scr/profilers/__init__.py
automatic_contract_creation/scr/profilers/profiler.py
automatic_contract_creation/scr/profilers/profiler_helper_click.py
automatic_contract_creation/scr/profilers/profiler_helper_trino.py
automatic_contract_creation/scr/utils/__init__.py
automatic_contract_creation/scr/utils/contract_structure.py
automatic_contract_creation/scr/utils/data_context_provider.py
automatic_contract_creation/scr/utils/omd_client.py
automatic_contract_creation/scr/utils/omd_entities.py
automatic_contract_creation/scr/utils/omd_exceptions.py
automatic_contract_creation-2.0.dist-info/METADATA
automatic_contract_creation-2.0.dist-info/WHEEL
automatic_contract_creation-2.0.dist-info/top_level.txt
automatic_contract_creation-2.0.dist-info/RECORD
